package/__init__.py
package/build.py
package/install_dev.py
package/install_git.py
package/publish.py
python_micro_script_template-0.0.2.dist-info/LICENSE.txt
python_micro_script_template-0.0.2.dist-info/METADATA
python_micro_script_template-0.0.2.dist-info/WHEEL
python_micro_script_template-0.0.2.dist-info/entry_points.txt
python_micro_script_template-0.0.2.dist-info/top_level.txt
python_micro_script_template-0.0.2.dist-info/RECORD
