Metadata-Version: 2.1
Name: python-micro-script-template
Version: 0.0.2
Summary: Template for a small installable script
Home-page: https://github.com/markuspeitl/python_micro_script_template
Author: Markus Peitl
Author-email: office@markuspeitl.com
Classifier: Programming Language :: Python :: 3
Classifier: Intended Audience :: Developers
Classifier: Natural Language :: English
Classifier: License :: OSI Approved :: MIT License
Classifier: Topic :: Software Development
Requires-Python: >=3
License-File: LICENSE.txt
Requires-Dist: twine
